agentic_chatbot/__init__.py
agentic_chatbot/advanced_conversation_agent.py
agentic_chatbot/context_agent.py
agentic_chatbot/model_selection_agent.py
agentic_chatbot/security_agent.py
agentic_chatbot-2.0.3.dist-info/licenses/LICENSE
examples/README.md
examples/__init__.py
examples/advanced_agent_examples.py
examples/agent_smoke_test.py
examples/eval_agents.py
examples/streamlit_demo.py
examples/data/sample_eval.jsonl
tests/__init__.py
tests/test_security_agent.py
agentic_chatbot-2.0.3.dist-info/METADATA
agentic_chatbot-2.0.3.dist-info/WHEEL
agentic_chatbot-2.0.3.dist-info/entry_points.txt
agentic_chatbot-2.0.3.dist-info/top_level.txt
agentic_chatbot-2.0.3.dist-info/RECORD
